Metadata-Version: 2.1
Name: zippy-form
Version: 1.0.0
Summary: Quick form-development package for django with no code.
Author: Karthick Sivakumar
Author-email: karthik@zaigoinfotech.com
Requires-Dist: Django (>=3.0.0)
Requires-Dist: djangorestframework (>=3.0.0)
Requires-Dist: jsonschema (>=4.17.3)
